this_django-0.1.0.dist-info/METADATA
this_django-0.1.0.dist-info/WHEEL
this_django/__init__.py
this_django-0.1.0.dist-info/RECORD
